ocr_correction/__init__.py
sparv_ocr_correction_plugin-0.1.0.dist-info/METADATA
sparv_ocr_correction_plugin-0.1.0.dist-info/WHEEL
sparv_ocr_correction_plugin-0.1.0.dist-info/entry_points.txt
sparv_ocr_correction_plugin-0.1.0.dist-info/licenses/LICENSE
sparv_ocr_correction_plugin-0.1.0.dist-info/RECORD
